{
  "trainers": [
    {
      "firstName": "Tony",
      "lastName": "Stark",
      "email": "tony@stark.com",
      "password": "secret",
      "gender": "male",
      "trainerId": "4ad52597-6d98-4d80-8673-084be55a87a0",
      "bookings": [
        {
          "bookingId": "786f6a39-6d5b-42d2-994c-61e86a9d4ec6",
          "memberId": "3ad52697-6d98-4d80-8273-084de55a86c0",
          "trainerId": "4ad52597-6d98-4d80-8673-084be55a87a0",
          "trainerFirstName": "Tony",
          "trainerLastName": "Stark",
          "memberFirstName": "Homer",
          "memberLastName": "Simpson",
          "bookingDate": "August 16, 2017",
          "bookingTime": "2:00 PM"
        }
      ]
    },
    {
      "firstName": "Steve",
      "lastName": "Rogers",
      "email": "steve@rogers.com",
      "password": "secret",
      "gender": "male",
      "trainerId": "4ad52337-6e17-4d80-8f78-084be25a4ad7",
      "bookings": []
    },
    {
      "firstName": "Natasha",
      "lastName": "Romanova",
      "email": "natasha@romanova.com",
      "password": "secret",
      "gender": "female",
      "trainerId": "1bd5638f-4e3a-4d90-5f78-1355a25a4d2e",
      "bookings": []
    }
  ]
}